{
  "daily_data": [
    {
      "date": "2025-12-22",
      "volume": 268565907,
      "volume_millions": 268.57
    },
    {
      "date": "2025-12-23",
      "volume": 315339323,
      "volume_millions": 315.34
    },
    {
      "date": "2025-12-24",
      "volume": 278792650,
      "volume_millions": 278.79
    },
    {
      "date": "2025-12-25",
      "volume": 312575023,
      "volume_millions": 312.58
    },
    {
      "date": "2025-12-26",
      "volume": 250135550,
      "volume_millions": 250.14
    },
    {
      "date": "2025-12-27",
      "volume": 124223481,
      "volume_millions": 124.22
    },
    {
      "date": "2025-12-28",
      "volume": 156440358,
      "volume_millions": 156.44
    },
    {
      "date": "2025-12-29",
      "volume": 342565416,
      "volume_millions": 342.57
    },
    {
      "date": "2025-12-30",
      "volume": 252267209,
      "volume_millions": 252.27
    },
    {
      "date": "2025-12-31",
      "volume": 247090988,
      "volume_millions": 247.09
    },
    {
      "date": "2026-01-01",
      "volume": 357145952,
      "volume_millions": 357.15
    },
    {
      "date": "2026-01-02",
      "volume": 255996087,
      "volume_millions": 256.0
    },
    {
      "date": "2026-01-03",
      "volume": 162300160,
      "volume_millions": 162.3
    },
    {
      "date": "2026-01-04",
      "volume": 118996246,
      "volume_millions": 119.0
    },
    {
      "date": "2026-01-05",
      "volume": 264612943,
      "volume_millions": 264.61
    },
    {
      "date": "2026-01-06",
      "volume": 359101141,
      "volume_millions": 359.1
    },
    {
      "date": "2026-01-07",
      "volume": 298971816,
      "volume_millions": 298.97
    },
    {
      "date": "2026-01-08",
      "volume": 262188151,
      "volume_millions": 262.19
    },
    {
      "date": "2026-01-09",
      "volume": 354674548,
      "volume_millions": 354.67
    },
    {
      "date": "2026-01-10",
      "volume": 141876735,
      "volume_millions": 141.88
    },
    {
      "date": "2026-01-11",
      "volume": 178740061,
      "volume_millions": 178.74
    },
    {
      "date": "2026-01-12",
      "volume": 309533232,
      "volume_millions": 309.53
    },
    {
      "date": "2026-01-13",
      "volume": 283994775,
      "volume_millions": 283.99
    },
    {
      "date": "2026-01-14",
      "volume": 318085973,
      "volume_millions": 318.09
    },
    {
      "date": "2026-01-15",
      "volume": 267445036,
      "volume_millions": 267.45
    },
    {
      "date": "2026-01-16",
      "volume": 359065021,
      "volume_millions": 359.07
    },
    {
      "date": "2026-01-17",
      "volume": 122668665,
      "volume_millions": 122.67
    },
    {
      "date": "2026-01-18",
      "volume": 153957179,
      "volume_millions": 153.96
    },
    {
      "date": "2026-01-19",
      "volume": 372778755,
      "volume_millions": 372.78
    },
    {
      "date": "2026-01-20",
      "volume": 314808216,
      "volume_millions": 314.81
    },
    {
      "date": "2026-01-21",
      "volume": 359226411,
      "volume_millions": 359.23
    },
    {
      "date": "2026-01-22",
      "volume": 318695134,
      "volume_millions": 318.7
    },
    {
      "date": "2026-01-23",
      "volume": 370688206,
      "volume_millions": 370.69
    },
    {
      "date": "2026-01-24",
      "volume": 193741177,
      "volume_millions": 193.74
    },
    {
      "date": "2026-01-25",
      "volume": 179340850,
      "volume_millions": 179.34
    },
    {
      "date": "2026-01-26",
      "volume": 314184053,
      "volume_millions": 314.18
    },
    {
      "date": "2026-01-27",
      "volume": 264726599,
      "volume_millions": 264.73
    },
    {
      "date": "2026-01-28",
      "volume": 280621640,
      "volume_millions": 280.62
    },
    {
      "date": "2026-01-29",
      "volume": 275968662,
      "volume_millions": 275.97
    },
    {
      "date": "2026-01-30",
      "volume": 385716828,
      "volume_millions": 385.72
    },
    {
      "date": "2026-01-31",
      "volume": 180711864,
      "volume_millions": 180.71
    },
    {
      "date": "2026-02-01",
      "volume": 180594695,
      "volume_millions": 180.59
    },
    {
      "date": "2026-02-02",
      "volume": 318664587,
      "volume_millions": 318.66
    },
    {
      "date": "2026-02-03",
      "volume": 342830665,
      "volume_millions": 342.83
    },
    {
      "date": "2026-02-04",
      "volume": 385844108,
      "volume_millions": 385.84
    },
    {
      "date": "2026-02-05",
      "volume": 379214956,
      "volume_millions": 379.21
    },
    {
      "date": "2026-02-06",
      "volume": 380736714,
      "volume_millions": 380.74
    },
    {
      "date": "2026-02-07",
      "volume": 170420539,
      "volume_millions": 170.42
    },
    {
      "date": "2026-02-08",
      "volume": 202729854,
      "volume_millions": 202.73
    },
    {
      "date": "2026-02-09",
      "volume": 356740560,
      "volume_millions": 356.74
    },
    {
      "date": "2026-02-10",
      "volume": 387541463,
      "volume_millions": 387.54
    },
    {
      "date": "2026-02-11",
      "volume": 332926644,
      "volume_millions": 332.93
    },
    {
      "date": "2026-02-12",
      "volume": 313157332,
      "volume_millions": 313.16
    },
    {
      "date": "2026-02-13",
      "volume": 352912160,
      "volume_millions": 352.91
    },
    {
      "date": "2026-02-14",
      "volume": 144673846,
      "volume_millions": 144.67
    },
    {
      "date": "2026-02-15",
      "volume": 218439080,
      "volume_millions": 218.44
    },
    {
      "date": "2026-02-16",
      "volume": 309059458,
      "volume_millions": 309.06
    },
    {
      "date": "2026-02-17",
      "volume": 357482564,
      "volume_millions": 357.48
    },
    {
      "date": "2026-02-18",
      "volume": 290533219,
      "volume_millions": 290.53
    },
    {
      "date": "2026-02-19",
      "volume": 409400606,
      "volume_millions": 409.4
    },
    {
      "date": "2026-02-20",
      "volume": 325241111,
      "volume_millions": 325.24
    },
    {
      "date": "2026-02-21",
      "volume": 183462797,
      "volume_millions": 183.46
    },
    {
      "date": "2026-02-22",
      "volume": 147699777,
      "volume_millions": 147.7
    },
    {
      "date": "2026-02-23",
      "volume": 309033395,
      "volume_millions": 309.03
    },
    {
      "date": "2026-02-24",
      "volume": 297645399,
      "volume_millions": 297.65
    },
    {
      "date": "2026-02-25",
      "volume": 322329175,
      "volume_millions": 322.33
    },
    {
      "date": "2026-02-26",
      "volume": 404715484,
      "volume_millions": 404.72
    },
    {
      "date": "2026-02-27",
      "volume": 410355681,
      "volume_millions": 410.36
    },
    {
      "date": "2026-02-28",
      "volume": 180932479,
      "volume_millions": 180.93
    },
    {
      "date": "2026-03-01",
      "volume": 210261854,
      "volume_millions": 210.26
    },
    {
      "date": "2026-03-02",
      "volume": 376397106,
      "volume_millions": 376.4
    },
    {
      "date": "2026-03-03",
      "volume": 418814509,
      "volume_millions": 418.81
    },
    {
      "date": "2026-03-04",
      "volume": 311947152,
      "volume_millions": 311.95
    },
    {
      "date": "2026-03-05",
      "volume": 301211633,
      "volume_millions": 301.21
    },
    {
      "date": "2026-03-06",
      "volume": 300510469,
      "volume_millions": 300.51
    },
    {
      "date": "2026-03-07",
      "volume": 185575297,
      "volume_millions": 185.58
    },
    {
      "date": "2026-03-08",
      "volume": 233939248,
      "volume_millions": 233.94
    },
    {
      "date": "2026-03-09",
      "volume": 342898580,
      "volume_millions": 342.9
    },
    {
      "date": "2026-03-10",
      "volume": 304433708,
      "volume_millions": 304.43
    },
    {
      "date": "2026-03-11",
      "volume": 330445394,
      "volume_millions": 330.45
    },
    {
      "date": "2026-03-12",
      "volume": 382935334,
      "volume_millions": 382.94
    },
    {
      "date": "2026-03-13",
      "volume": 314782981,
      "volume_millions": 314.78
    },
    {
      "date": "2026-03-14",
      "volume": 218698681,
      "volume_millions": 218.7
    },
    {
      "date": "2026-03-15",
      "volume": 150453632,
      "volume_millions": 150.45
    },
    {
      "date": "2026-03-16",
      "volume": 413252818,
      "volume_millions": 413.25
    },
    {
      "date": "2026-03-17",
      "volume": 358373354,
      "volume_millions": 358.37
    },
    {
      "date": "2026-03-18",
      "volume": 349017073,
      "volume_millions": 349.02
    },
    {
      "date": "2026-03-19",
      "volume": 328557586,
      "volume_millions": 328.56
    },
    {
      "date": "2026-03-20",
      "volume": 423194060,
      "volume_millions": 423.19
    },
    {
      "date": "2026-03-21",
      "volume": 222615845,
      "volume_millions": 222.62
    }
  ],
  "weekly_data": [
    {
      "week_start": "2025-12-22",
      "volume": 1706072292,
      "volume_millions": 1706.07,
      "volume_billions": 1.706
    },
    {
      "week_start": "2025-12-29",
      "volume": 1736362058,
      "volume_millions": 1736.36,
      "volume_billions": 1.736
    },
    {
      "week_start": "2026-01-05",
      "volume": 1860165395,
      "volume_millions": 1860.17,
      "volume_billions": 1.86
    },
    {
      "week_start": "2026-01-12",
      "volume": 1814749881,
      "volume_millions": 1814.75,
      "volume_billions": 1.815
    },
    {
      "week_start": "2026-01-19",
      "volume": 2109278749,
      "volume_millions": 2109.28,
      "volume_billions": 2.109
    },
    {
      "week_start": "2026-01-26",
      "volume": 1882524341,
      "volume_millions": 1882.52,
      "volume_billions": 1.883
    },
    {
      "week_start": "2026-02-02",
      "volume": 2180441423,
      "volume_millions": 2180.44,
      "volume_billions": 2.18
    },
    {
      "week_start": "2026-02-09",
      "volume": 2106391085,
      "volume_millions": 2106.39,
      "volume_billions": 2.106
    },
    {
      "week_start": "2026-02-16",
      "volume": 2022879532,
      "volume_millions": 2022.88,
      "volume_billions": 2.023
    },
    {
      "week_start": "2026-02-23",
      "volume": 2135273467,
      "volume_millions": 2135.27,
      "volume_billions": 2.135
    },
    {
      "week_start": "2026-03-02",
      "volume": 2128395414,
      "volume_millions": 2128.4,
      "volume_billions": 2.128
    },
    {
      "week_start": "2026-03-09",
      "volume": 2044648310,
      "volume_millions": 2044.65,
      "volume_billions": 2.045
    },
    {
      "week_start": "2026-03-16",
      "volume": 2095010736,
      "volume_millions": 2095.01,
      "volume_billions": 2.095
    }
  ],
  "metrics": {
    "volume_24h": 277125256,
    "volume_24h_millions": 277.13,
    "open_interest": 520091540,
    "open_interest_millions": 520.09,
    "active_markets": 837,
    "estimated_daily_revenue": 5542505.12
  },
  "source": "Generated from historical patterns (API unavailable)",
  "last_updated": "2026-03-22 06:42:26 UTC",
  "update_frequency": "Daily via GitHub Actions",
  "note": "Volume data based on Kalshi market patterns (~$2B weekly)"
}